pytest_forward_compatability.py
pytest_forward_compatability-0.1.0.dist-info/LICENSE
pytest_forward_compatability-0.1.0.dist-info/WHEEL
pytest_forward_compatability-0.1.0.dist-info/METADATA
pytest_forward_compatability-0.1.0.dist-info/RECORD
